gerrit_review_robot/__init__.py
gerrit_review_robot/gerrit.py
gerrit_review_robot/gerrit_review_robot.py
gerrit_review_robot/helpers/__init__.py
gerrit_review_robot/helpers/condense.py
test/__init__.py
test/test_condense.py
test/test_gerrit_robot.py
gerrit_review_robot-0.0.7.dist-info/LICENSE
gerrit_review_robot-0.0.7.dist-info/METADATA
gerrit_review_robot-0.0.7.dist-info/WHEEL
gerrit_review_robot-0.0.7.dist-info/top_level.txt
gerrit_review_robot-0.0.7.dist-info/RECORD
