Metadata-Version: 2.1
Name: gerrit-review-robot
Version: 0.0.7
Summary: A framework for writing bots, that review a code base and post the review together with comments to Gerrit.
Home-page: https://github.com/tom-010/gerrit_review_robot
Author: Thomas Deniffel
Author-email: tdeniffel@gmail.com
License: Apache2
Platform: UNKNOWN
Classifier: Development Status :: 4 - Beta
Classifier: Intended Audience :: Developers
Classifier: Programming Language :: Python
Classifier: Programming Language :: Python :: 3 :: Only
Classifier: Programming Language :: Python :: 3.6
Classifier: Programming Language :: Python :: 3.7
Requires-Python: >=3
License-File: LICENSE
Requires-Dist: requests
Requires-Dist: easy-exec
Requires-Dist: git-diff-lines
